javi_oscars2/oscars.py
javi_oscars2/settings.py
javi_oscars2-0.0.2.dist-info/METADATA
javi_oscars2-0.0.2.dist-info/WHEEL
javi_oscars2-0.0.2.dist-info/RECORD
